css/__init__.py
css/_typing.py
css/_version.py
css/config.py
css/config.schema.json
css/core.py
css/param_estimator.py
css/py.typed
css/score.py
css/serving/__init__.py
css/serving/app.py
css/serving/content_types.py
css/serving/decoder.py
css/serving/encoder.py
css/serving/errors.py
css/serving/model_cache.py
css/serving/utils.py
css_mini-0.1.0a2.dist-info/LICENSE.txt
css_mini-0.1.0a2.dist-info/METADATA
css_mini-0.1.0a2.dist-info/WHEEL
css_mini-0.1.0a2.dist-info/entry_points.txt
css_mini-0.1.0a2.dist-info/top_level.txt
css_mini-0.1.0a2.dist-info/RECORD
