Metadata-Version: 2.1
Name: css-mini
Version: 0.1.0a2
Summary: Customer Success Scorecard
Author-email: Collin Cunningham <collin.cunningham@salesforce.com>
License: Apache License Version 2.0
Classifier: Development Status :: 4 - Beta
Classifier: Operating System :: Unix
Classifier: Programming Language :: Python
Classifier: Programming Language :: Python :: 3
Classifier: Programming Language :: Python :: 3.10
Classifier: Programming Language :: Python :: 3.11
Classifier: Programming Language :: Python :: 3.12
Requires-Python: >=3.10
License-File: LICENSE.txt
Requires-Dist: numpy
Requires-Dist: pandas
Requires-Dist: pydantic
Requires-Dist: scipy
Requires-Dist: scikit-learn
Requires-Dist: PyYAML
Provides-Extra: deploy
Requires-Dist: boto3; extra == "deploy"
Requires-Dist: sagemaker; extra == "deploy"
Requires-Dist: sagemaker-training; extra == "deploy"
Requires-Dist: flask; extra == "deploy"
Provides-Extra: dev
Requires-Dist: build; extra == "dev"
Requires-Dist: pre-commit; extra == "dev"
Requires-Dist: pytest; extra == "dev"
Requires-Dist: pytest-cov; extra == "dev"
Requires-Dist: mypy; extra == "dev"
Requires-Dist: types-PyYAML; extra == "dev"
Requires-Dist: pytest-html; extra == "dev"
Requires-Dist: pytest-xdist; extra == "dev"
